sphinx_minify/__init__.py
sphinx_minify/sphinx_minify.py
sphinx_minify-0.0.1.dist-info/AUTHORS
sphinx_minify-0.0.1.dist-info/LICENSE
sphinx_minify-0.0.1.dist-info/METADATA
sphinx_minify-0.0.1.dist-info/WHEEL
sphinx_minify-0.0.1.dist-info/entry_points.txt
sphinx_minify-0.0.1.dist-info/pbr.json
sphinx_minify-0.0.1.dist-info/top_level.txt
sphinx_minify-0.0.1.dist-info/RECORD
