Metadata-Version: 2.1
Name: sphinx-minify
Version: 0.0.1
Summary: Minify Sphinx HTML output to save bandwidth
Home-page: https://open.telekom.cloud/
Author: Open Telekom Cloud
Classifier: Environment :: OpenStack
Classifier: Intended Audience :: Information Technology
Classifier: Intended Audience :: System Administrators
Classifier: License :: OSI Approved :: Apache Software License
Classifier: Operating System :: POSIX :: Linux
Classifier: Programming Language :: Python
Classifier: Programming Language :: Python :: 3
Classifier: Programming Language :: Python :: 3.7
Classifier: Programming Language :: Python :: 3.8
Classifier: Programming Language :: Python :: 3.9
Classifier: Programming Language :: Python :: 3 :: Only
Classifier: Programming Language :: Python :: Implementation :: CPython
Requires-Python: >=3.6
License-File: LICENSE
License-File: AUTHORS
Requires-Dist: pbr (>=2.0)
Requires-Dist: rjsmin (>=1.2.2)
Requires-Dist: rcssmin (>=1.1.2)
Requires-Dist: htmlmin (>=0.1.12)
